requests_util/__init__.py
requests_util/requests_util.py
requests_util-2.4.0.dist-info/METADATA
requests_util-2.4.0.dist-info/WHEEL
requests_util-2.4.0.dist-info/top_level.txt
requests_util-2.4.0.dist-info/RECORD
