Metadata-Version: 2.1
Name: requests-util
Version: 2.4.0
Summary: Typosquatting talk example, do not use.
Home-page: https://github.com/psf/requests
Author: Fake Package
Author-email: fake.package@dont.use
License: Apache
Classifier: Programming Language :: Python
Classifier: Programming Language :: Python :: 3
